tamarin/__init__.py
tamarin/status.py
tamarin/command/__init__.py
tamarin/command/apps.py
tamarin/command/command.py
tamarin/command/tests.py
tamarin/connections/__init__.py
tamarin/connections/apps.py
tamarin/connections/client.py
tamarin/connections/tests.py
tamarin/connections/functions/__init__.py
tamarin/connections/functions/error.py
tamarin/connections/functions/metadata.py
tamarin/connections/migrations/__init__.py
tamarin/cryptography/__init__.py
tamarin/cryptography/rsa.py
tamarin/database/__init__.py
tamarin/database/apps.py
tamarin/database/middleware/__init__.py
tamarin/database/middleware/mixin.py
tamarin/database/middleware/pinning_router_middleware.py
tamarin/database/migrations/__init__.py
tamarin/database/router/__init__.py
tamarin/database/router/pinning_replica_router.py
tamarin/database/router/replica_router.py
tamarin/database/router/utils.py
tamarin/database/tests/__init__.py
tamarin/database/tests/multi_database_test.py
tamarin/elasticsearch/__init__.py
tamarin/elasticsearch/apps.py
tamarin/elasticsearch/client.py
tamarin/elasticsearch/commands.py
tamarin/elasticsearch/config.py
tamarin/elasticsearch/tests.py
tamarin/elasticsearch/utils/__init__.py
tamarin/elasticsearch/utils/functions/__init__.py
tamarin/elasticsearch/utils/functions/validate_status.py
tamarin/elasticsearch/utils/functions/var2str.py
tamarin/firebase/__init__.py
tamarin/firebase/apps.py
tamarin/firebase/tests.py
tamarin/firebase/client/__init__.py
tamarin/firebase/client/firestore.py
tamarin/firebase/client/messaging.py
tamarin/lamagram/__init__.py
tamarin/lamagram/apps.py
tamarin/lamagram/bot.py
tamarin/lamagram/commands.py
tamarin/lamagram/config.py
tamarin/lamagram/logger.py
tamarin/lamagram/utils/__init__.py
tamarin/lamagram/utils/functions/__init__.py
tamarin/lamagram/utils/functions/validate_status.py
tamarin/logs/__init__.py
tamarin/logs/admin.py
tamarin/logs/api.py
tamarin/logs/apps.py
tamarin/logs/commands.py
tamarin/logs/db_router.py
tamarin/logs/models.py
tamarin_utils-0.15.5.dist-info/METADATA
tamarin_utils-0.15.5.dist-info/WHEEL
tamarin_utils-0.15.5.dist-info/top_level.txt
tamarin_utils-0.15.5.dist-info/RECORD
