Metadata-Version: 2.1
Name: tamarin-utils
Version: 0.15.5
Summary: Lamasoo utils for developing web application
Home-page: https://git.lamasoo.com/crs-agency/tamarin
Author: Lamasoo team
Author-email: tech@lamasoo.com
License: UNKNOWN
Platform: UNKNOWN
Classifier: Environment :: Web Environment
Classifier: Programming Language :: Python :: 3
Classifier: License :: OSI Approved :: MIT License
Classifier: Operating System :: OS Independent
Classifier: Framework :: Django
Classifier: Intended Audience :: Developers
Classifier: Topic :: Internet :: WWW/HTTP
Requires-Python: >=3.6
Requires-Dist: requests
Requires-Dist: djangorestframework
Requires-Dist: elasticsearch[async]
Requires-Dist: celery
Requires-Dist: sentry-sdk
Requires-Dist: python-dateutil
Requires-Dist: firebase-admin
Requires-Dist: google-api-python-client
Requires-Dist: python-jose
Requires-Dist: djangorestframework-simplejwt
Requires-Dist: pycryptodome
Requires-Dist: django-nose
Requires-Dist: python-telegram-bot
Requires-Dist: Pyrogram
Requires-Dist: TgCrypto
Requires-Dist: elastic-apm
Requires-Dist: xlwt
